LICENSE
MANIFEST.in
README.md
setup.py
eirStru/__init__.py
eirStru/__version__.py
eirStru/aiomysql_helper.py
eirStru/captcha_intf.py
eirStru/common.py
eirStru/eirjob_intf.py
eirStru/eirlogin_intf.py
eirStru/redis_utils.py
eirStru/sendemail_intf.py
eirStru/test.py
eirStru/utils.py
eirStru/wx_push.py
eirStru.egg-info/PKG-INFO
eirStru.egg-info/SOURCES.txt
eirStru.egg-info/dependency_links.txt
eirStru.egg-info/top_level.txt